Metadata-Version: 2.1
Name: imgbb
Version: 1.2
Summary: Simple API Wrapper for ImgBB service
Home-page: UNKNOWN
Author-email: avebhs.ru@gmail.com
License: UNKNOWN
Platform: UNKNOWN
